nsdev/__init__.py
nsjprdev-0.1.1.dist-info/METADATA
nsjprdev-0.1.1.dist-info/WHEEL
nsjprdev-0.1.1.dist-info/top_level.txt
nsjprdev-0.1.1.dist-info/RECORD
